ensemble_boxes/__init__.py
ensemble_boxes/ensemble_boxes_nms.py
ensemble_boxes/ensemble_boxes_nms_pytorch.py
ensemble_boxes/ensemble_boxes_nmw.py
ensemble_boxes/ensemble_boxes_wbf.py
ensemble_boxes/ensemble_boxes_wbf_1d.py
ensemble_boxes/ensemble_boxes_wbf_3d.py
ensemble_boxes/ensemble_boxes_wbf_experimental.py
ensemble_boxes/ensemble_boxes_wbf_pytorch.py
ensemble_boxes-1.0.9.dist-info/LICENSE
ensemble_boxes-1.0.9.dist-info/METADATA
ensemble_boxes-1.0.9.dist-info/WHEEL
ensemble_boxes-1.0.9.dist-info/top_level.txt
ensemble_boxes-1.0.9.dist-info/RECORD
